karrio/mappers/parcelone/__init__.py
karrio/mappers/parcelone/mapper.py
karrio/mappers/parcelone/proxy.py
karrio/mappers/parcelone/settings.py
karrio/plugins/parcelone/__init__.py
karrio/providers/parcelone/__init__.py
karrio/providers/parcelone/error.py
karrio/providers/parcelone/rate.py
karrio/providers/parcelone/tracking.py
karrio/providers/parcelone/units.py
karrio/providers/parcelone/utils.py
karrio/providers/parcelone/shipment/__init__.py
karrio/providers/parcelone/shipment/cancel.py
karrio/providers/parcelone/shipment/create.py
karrio/schemas/parcelone/__init__.py
karrio/schemas/parcelone/error.py
karrio/schemas/parcelone/shipping_request.py
karrio/schemas/parcelone/shipping_response.py
karrio/schemas/parcelone/tracking_response.py
modules/connectors/parcelone/karrio/schemas/__init__.py
modules/connectors/parcelone/karrio/schemas/parcelone/__init__.py
karrio_parcelone-2026.1.4.dist-info/METADATA
karrio_parcelone-2026.1.4.dist-info/WHEEL
karrio_parcelone-2026.1.4.dist-info/entry_points.txt
karrio_parcelone-2026.1.4.dist-info/top_level.txt
karrio_parcelone-2026.1.4.dist-info/RECORD
